{
  "author": "WenXin2",
  "forClass": "com.legacy.blue_skies.client.models.entities.hostile.DiophydeProwlerModel",
  "leftHandParts": [
    {
      "fieldName": "frontLeftLeg",
      "placementCorrectors": [
        {
          "type": "translate",
          "axis": "x",
          "amount": 0.125
        },
        {
          "type": "translate",
          "axis": "y",
          "amount": -0.75
        },
        {
          "type": "translate",
          "axis": "z",
          "amount": 0.6875
        }
      ]
    }
  ],
  "rightHandParts": [
    {
      "fieldName": "frontRightLeg",
      "placementCorrectors": [
        {
          "type": "translate",
          "axis": "x",
          "amount": -0.13124999403953552
        },
        {
          "type": "translate",
          "axis": "y",
          "amount": -0.75
        },
        {
          "type": "translate",
          "axis": "z",
          "amount": 0.6875
        }
      ]
    }
  ]
}